RedXAISecureToolkit/__init__.py
RedXAISecureToolkit/test.py
RedXAISecureToolkit/FireCloud/RedXAIFireCloud.py
RedXAISecureToolkit/FireCloud/__init__.py
RedXAISecureToolkit/SecurePayments/RedXAISecurePayments.py
RedXAISecureToolkit/SecurePayments/__init__.py
RedXAISecureToolkit/SecureUpdater/__init__.py
redxaisecuretoolkit-1.0.0.dist-info/licenses/LICENSE
redxaisecuretoolkit-1.0.0.dist-info/METADATA
redxaisecuretoolkit-1.0.0.dist-info/WHEEL
redxaisecuretoolkit-1.0.0.dist-info/top_level.txt
redxaisecuretoolkit-1.0.0.dist-info/RECORD
