Metadata-Version: 2.4
Name: RedXAISecureToolkit
Version: 1.0.0
Summary: A unified toolkit for Firebase/Google Cloud, secure payments, and updates.
Home-page: https://github.com/YourUsername/RedXAISecureToolkit
Author: YourName
Author-email: youremail@example.com
Classifier: Programming Language :: Python :: 3
Classifier: License :: OSI Approved :: MIT License
Classifier: Operating System :: OS Independent
Requires-Python: >=3.7
License-File: LICENSE
Requires-Dist: firebase-admin
Requires-Dist: google-cloud-storage
Requires-Dist: stripe
Requires-Dist: requests
Requires-Dist: python-dotenv
Dynamic: author
Dynamic: author-email
Dynamic: classifier
Dynamic: description
Dynamic: description-content-type
Dynamic: home-page
Dynamic: license-file
Dynamic: requires-dist
Dynamic: requires-python
Dynamic: summary
